ansi_string/__init__.py
ansi_string/ansi_format.py
ansi_string/ansi_param.py
ansi_string/ansi_parsing.py
ansi_string/ansi_string.py
ansi_string/utils.py
ansi_string-1.1.12.dist-info/METADATA
ansi_string-1.1.12.dist-info/WHEEL
ansi_string-1.1.12.dist-info/top_level.txt
ansi_string-1.1.12.dist-info/RECORD
